nanodoc/__init__.py
nanodoc/__main__.py
nanodoc/boot.py
nanodoc/cli.py
nanodoc/core.py
nanodoc/docs/HELP.txt
nanodoc/docs/guides/manifesto.txt
nanodoc/docs/guides/quickstart.md
nanodoc/docs/guides/selecting-files.txt
nanodoc/document.py
nanodoc/extractor.py
nanodoc/formatter.py
nanodoc/legacy.py
nanodoc/renderer.py
nanodoc/resolver.py
nanodoc/structures.py
nanodoc/themes/classic-dark.yaml
nanodoc/themes/classic-light.yaml
nanodoc/themes/classic.yaml
nanodoc/version.py
nanodoc-0.9.7.dist-info/LICENSE
nanodoc-0.9.7.dist-info/METADATA
nanodoc-0.9.7.dist-info/WHEEL
nanodoc-0.9.7.dist-info/entry_points.txt
nanodoc-0.9.7.dist-info/RECORD
