Metadata-Version: 2.3
Name: nanodoc
Version: 0.9.7
Summary: A minimalist document bundler designed for stitching hints, reminders and short docs.
Home-page: https://github.com/arthur-debert/nanodoc/
License: # License
Keywords: documentation,bundler,minimalist,text,prompts
Author: Arthur Debert
Author-email: arthur@debert.xyz
Requires-Python: >=3.9
Classifier: Development Status :: 4 - Beta
Classifier: Intended Audience :: Developers
Classifier: License :: OSI Approved :: MIT License
Classifier: Programming Language :: Python :: 3
Classifier: Programming Language :: Python :: 3.9
Classifier: Topic :: Documentation
Classifier: Topic :: Text Processing :: Markup
Provides-Extra: dev
Requires-Dist: black (>=25.1.0,<26.0.0) ; extra == "dev"
Requires-Dist: click (>=8.1.7,<9.0.0)
Requires-Dist: jinja2 (>=3.1.6,<4.0.0) ; extra == "dev"
Requires-Dist: pre-commit (>=4.1.0,<5.0.0) ; extra == "dev"
Requires-Dist: pytest (>=8.3.5,<9.0.0) ; extra == "dev"
Requires-Dist: pytest-cov (>=4.1.0,<5.0.0) ; extra == "dev"
Requires-Dist: pyyaml (>=6.0.0,<7.0.0)
Requires-Dist: rich (>=13.9.4,<14.0.0)
Requires-Dist: ruff (>=0.3.2,<0.4.0) ; extra == "dev"
Requires-Dist: twine (>=6.1.0,<7.0.0) ; extra == "dev"
Project-URL: Bug Tracker, https://github.com/arthur-debert/nanodoc/issues
Project-URL: Repository, https://github.com/arthur-debert/nanodoc/
